LICENSE
pq_dashboard/__init__.py
pq_dashboard/cli/__init__.py
pq_dashboard/cli/commands.py
pq_dashboard/config.py
pq_dashboard/connection.py
pq_dashboard/data/items.py
pq_dashboard/data/queues.py
pq_dashboard/frontend/README.md
pq_dashboard/frontend/esbuild.config.js
pq_dashboard/frontend/esbuild.proxy.js
pq_dashboard/frontend/package-lock.json
pq_dashboard/frontend/package.json
pq_dashboard/frontend/tailwind.config.js
pq_dashboard/frontend/www/assets/.gitkeep
pq_dashboard/frontend/www/assets/ReactToastify.css
pq_dashboard/frontend/www/assets/favicon.png
pq_dashboard/frontend/www/assets/index.js
pq_dashboard/frontend/www/assets/styles.css
pq_dashboard/frontend/www/index.html
pq_dashboard/main.py
pq_dashboard/routers/health.py
pq_dashboard/routers/items.py
pq_dashboard/routers/queues.py
pq_dashboard/schema/__init__.py
pq_dashboard/schema/item.py
pq_dashboard/schema/queue.py
pq_dashboard-0.1.1.dist-info/entry_points.txt
pq_dashboard-0.1.1.dist-info/LICENSE
pq_dashboard-0.1.1.dist-info/WHEEL
pq_dashboard-0.1.1.dist-info/METADATA
pq_dashboard-0.1.1.dist-info/RECORD
