Metadata-Version: 2.1
Name: pq-dashboard
Version: 0.1.1
Summary: Web dashboard and CLI utility for managing PQ queues
Home-page: https://github.com/MisterKeefe/pq-dashboard
License: MIT
Keywords: pq,dashboard,postgres
Author: Tom Keefe
Author-email: 8655118+MisterKeefe@users.noreply.github.com
Requires-Python: >=3.7,<4.0
Classifier: Environment :: Console
Classifier: Environment :: Web Environment
Classifier: Intended Audience :: Developers
Classifier: License :: OSI Approved :: MIT License
Classifier: Operating System :: OS Independent
Classifier: Programming Language :: JavaScript
Classifier: Programming Language :: Python :: 3
Classifier: Programming Language :: Python :: 3.7
Classifier: Programming Language :: Python :: 3.8
Classifier: Programming Language :: Python :: 3.9
Classifier: Programming Language :: SQL
Classifier: Topic :: Database :: Front-Ends
Requires-Dist: aiofiles (>=0.7.0,<0.8.0)
Requires-Dist: fastapi (>=0.67.0,<0.68.0)
Requires-Dist: psycopg2 (>=2.9.1,<3.0.0)
Requires-Dist: pydantic (>=1.8.2,<2.0.0)
Requires-Dist: pytest-postgresql (>=3.1.1,<4.0.0)
Requires-Dist: uvicorn[standard] (>=0.14.0,<0.15.0)
Project-URL: Repository, https://github.com/MisterKeefe/pq-dashboard
